pytoque/__init__.py
pytoque/core/__init__.py
pytoque/core/core.py
pytoque/core/scrap.py
pytoque/libs/__init__.py
pytoque/libs/cache.py
pytoque/utils/__init__.py
pytoque/utils/utils.py
pytoque/validators/__init__.py
pytoque/validators/validators.py
pytoque-0.2.0.dist-info/LICENSE
pytoque-0.2.0.dist-info/METADATA
pytoque-0.2.0.dist-info/WHEEL
pytoque-0.2.0.dist-info/top_level.txt
pytoque-0.2.0.dist-info/RECORD
