Metadata-Version: 2.1
Name: pytoque
Version: 0.2.0
Summary: A package that facilitates requests and has some tools for the El-Toque API
Home-page: https://github.com/LeivSuaxy/pytoque
Author: jleivsuaxy
Author-email: jleivsuaxy@gmail.com
Classifier: Programming Language :: Python :: 3
Classifier: License :: OSI Approved :: MIT License
Classifier: Operating System :: OS Independent
Requires-Python: >=3.11
License-File: LICENSE
Requires-Dist: certifi==2024.8.30
Requires-Dist: charset-normalizer==3.4.0
Requires-Dist: idna==3.10
Requires-Dist: requests==2.32.3
Requires-Dist: urllib3==2.2.3
Requires-Dist: beautifulsoup4==4.13.3
Requires-Dist: setuptools==75.6.0
Requires-Dist: soupsieve==2.6
Requires-Dist: typing_extensions==4.12.2
